aiqpy
tools
