Metadata-Version: 1.0
Name: aiqpy
Version: 0.8.1
Summary: Python bindings for connecting to a AIQ8 server
Home-page: UNKNOWN
Author: Erik Lundberg
Author-email: lundbergerik@gmail.com
License: UNKNOWN
Keywords: aiq8,appear,rest,api
Platform: UNKNOWN
